opentelemetry/instrumentation/mistralai/__init__.py
opentelemetry/instrumentation/mistralai/config.py
opentelemetry/instrumentation/mistralai/event_emitter.py
opentelemetry/instrumentation/mistralai/event_models.py
opentelemetry/instrumentation/mistralai/span_utils.py
opentelemetry/instrumentation/mistralai/utils.py
opentelemetry/instrumentation/mistralai/version.py
opentelemetry_instrumentation_mistralai-0.51.1.dist-info/METADATA
opentelemetry_instrumentation_mistralai-0.51.1.dist-info/WHEEL
opentelemetry_instrumentation_mistralai-0.51.1.dist-info/entry_points.txt
opentelemetry_instrumentation_mistralai-0.51.1.dist-info/RECORD
