Metadata-Version: 2.4
Name: opentelemetry-instrumentation-mistralai
Version: 0.51.1
Summary: OpenTelemetry Mistral AI instrumentation
Project-URL: Repository, https://github.com/traceloop/openllmetry/tree/main/packages/opentelemetry-instrumentation-mistralai
Author-email: Gal Kleinman <gal@traceloop.com>, Nir Gazit <nir@traceloop.com>
License-Expression: Apache-2.0
Requires-Python: <4,>=3.10
Requires-Dist: opentelemetry-api<2,>=1.38.0
Requires-Dist: opentelemetry-instrumentation>=0.59b0
Requires-Dist: opentelemetry-semantic-conventions-ai<0.5.0,>=0.4.13
Requires-Dist: opentelemetry-semantic-conventions>=0.59b0
Provides-Extra: instruments
Requires-Dist: mistralai; extra == 'instruments'
